{"associated": {"location": {"lon": -70.79141, "lat": 42.9376373334092}, "runInitializationTimestamp": 1692230400}, "data": {"rating": [{"timestamp": 1692244800, "utcOffset": -4, "rating": {"key": "POOR_TO_FAIR", "value": 2}}, {"timestamp": 1692248400, "utcOffset": -4, "rating": {"key": "POOR_TO_FAIR", "value": 1.67}}, {"timestamp": 1692252000, "utcOffset": -4, "rating": {"key": "POOR_TO_FAIR", "value": 1.67}}, {"timestamp": 1692255600, "utcOffset": -4, "rating": {"key": "POOR_TO_FAIR", "value": 1.5}}, {"timestamp": 1692259200, "utcOffset": -4, "rating": {"key": "POOR_TO_FAIR", "value": 1.5}}, {"timestamp": 1692262800, "utcOffset": -4, "rating": {"key": "POOR", "value": 1.17}}, {"timestamp": 1692266400, "utcOffset": -4, "rating": {"key": "POOR", "value": 1}}, {"timestamp": 1692270000, "utcOffset": -4, "rating": {"key": "VERY_POOR", "value": 0}}, {"timestamp": 1692273600, "utcOffset": -4, "rating": {"key": "VERY_POOR", "value": 0}}, {"timestamp": 1692277200, "utcOffset": -4, "rating": {"key": "VERY_POOR", "value": 0}}, {"timestamp": 1692280800, "utcOffset": -4, "rating": {"key": "VERY_POOR", "value": 0}}, {"timestamp": 1692284400, "utcOffset": -4, "rating": {"key": "VERY_POOR", "value": 0}}, {"timestamp": 1692288000, "utcOffset": -4, "rating": {"key": "VERY_POOR", "value": 0}}, {"timestamp": 1692291600, "utcOffset": -4, "rating": {"key": "VERY_POOR", "value": 0.17}}, {"timestamp": 1692295200, "utcOffset": -4, "rating": {"key": "VERY_POOR", "value": 0.33}}, {"timestamp": 1692298800, "utcOffset": -4, "rating": {"key": "POOR", "value": 0.5}}, {"timestamp": 1692302400, "utcOffset": -4, "rating": {"key": "POOR", "value": 0.5}}, {"timestamp": 1692306000, "utcOffset": -4, "rating": {"key": "POOR", "value": 0.83}}, {"timestamp": 1692309600, "utcOffset": -4, "rating": {"key": "POOR", "value": 1}}, {"timestamp": 1692313200, "utcOffset": -4, "rating": {"key": "POOR", "value": 1}}, {"timestamp": 1692316800, "utcOffset": -4, "rating": {"key": "POOR", "value": 1}}, {"timestamp": 1692320400, "utcOffset": -4, "rating": {"key": "POOR", "value": 1}}, {"timestamp": 1692324000, "utcOffset": -4, "rating": {"key": "POOR", "value": 1}}, {"timestamp": 1692327600, "utcOffset": -4, "rating": {"key": "POOR", "value": 0.83}}]}, "permissions": {"data": [], "violations": [{"code": 4001, "message": "User does not have optional permission:sl_premium-forecasts", "permission": {"name": "sl_premium-forecasts", "required": false}}, {"code": 4001, "message": "User does not have optional permission:sl_premium-cams", "permission": {"name": "sl_premium-cams", "required": false}}]}}