{"associated": {"units": {"temperature": "F", "tideHeight": "FT", "swellHeight": "FT", "waveHeight": "FT", "windSpeed": "KTS", "pressure": "MB"}, "utcOffset": -4, "location": {"lon": -71.45312118111178, "lat": 41.434181432898335}, "runInitializationTimestamp": 1683784800}, "data": {"wind": [{"timestamp": 1683777600, "utcOffset": -4, "speed": 7.51883, "direction": 240.60049, "directionType": "Cross-shore", "gust": 22.74299, "optimalScore": 0}, {"timestamp": 1683781200, "utcOffset": -4, "speed": 6.83356, "direction": 240.70051, "directionType": "Cross-shore", "gust": 19.43845, "optimalScore": 0}, {"timestamp": 1683784800, "utcOffset": -4, "speed": 4.65758, "direction": 236.68182, "directionType": "Cross-shore", "gust": 13.02376, "optimalScore": 2}, {"timestamp": 1683788400, "utcOffset": -4, "speed": 6.13315, "direction": 239.76924, "directionType": "Cross-shore", "gust": 18.07776, "optimalScore": 0}, {"timestamp": 1683792000, "utcOffset": -4, "speed": 6.71837, "direction": 238.98242, "directionType": "Cross-shore", "gust": 15.35638, "optimalScore": 0}, {"timestamp": 1683795600, "utcOffset": -4, "speed": 6.43906, "direction": 242.4997, "directionType": "Cross-shore", "gust": 9.91361, "optimalScore": 0}, {"timestamp": 1683799200, "utcOffset": -4, "speed": 5.5778, "direction": 247.81869, "directionType": "Cross-shore", "gust": 9.13607, "optimalScore": 0}, {"timestamp": 1683802800, "utcOffset": -4, "speed": 5.1713, "direction": 245.09454, "directionType": "Cross-shore", "gust": 8.35853, "optimalScore": 0}, {"timestamp": 1683806400, "utcOffset": -4, "speed": 4.713, "direction": 245.69347, "directionType": "Cross-shore", "gust": 15.16199, "optimalScore": 2}, {"timestamp": 1683810000, "utcOffset": -4, "speed": 5.79111, "direction": 240.71138, "directionType": "Cross-shore", "gust": 13.41253, "optimalScore": 0}, {"timestamp": 1683813600, "utcOffset": -4, "speed": 6.15243, "direction": 236.45363, "directionType": "Cross-shore", "gust": 13.8013, "optimalScore": 0}, {"timestamp": 1683817200, "utcOffset": -4, "speed": 6.73732, "direction": 232.35814, "directionType": "Cross-shore", "gust": 13.02376, "optimalScore": 0}, {"timestamp": 1683820800, "utcOffset": -4, "speed": 7.41399, "direction": 230.39579, "directionType": "Cross-shore", "gust": 12.82938, "optimalScore": 0}, {"timestamp": 1683824400, "utcOffset": -4, "speed": 8.34241, "direction": 227.09887, "directionType": "Cross-shore", "gust": 14.38446, "optimalScore": 0}, {"timestamp": 1683828000, "utcOffset": -4, "speed": 8.6173, "direction": 227.51182, "directionType": "Cross-shore", "gust": 15.16199, "optimalScore": 0}, {"timestamp": 1683831600, "utcOffset": -4, "speed": 9.0864, "direction": 222.82938, "directionType": "Cross-shore", "gust": 14.38446, "optimalScore": 0}, {"timestamp": 1683835200, "utcOffset": -4, "speed": 10.36184, "direction": 217.24696, "directionType": "Cross-shore", "gust": 15.93953, "optimalScore": 0}, {"timestamp": 1683838800, "utcOffset": -4, "speed": 10.01323, "direction": 221.89888, "directionType": "Cross-shore", "gust": 21.57668, "optimalScore": 0}, {"timestamp": 1683842400, "utcOffset": -4, "speed": 8.65901, "direction": 220.5104, "directionType": "Cross-shore", "gust": 22.35422, "optimalScore": 0}, {"timestamp": 1683846000, "utcOffset": -4, "speed": 7.58523, "direction": 220.74379, "directionType": "Cross-shore", "gust": 19.43845, "optimalScore": 0}, {"timestamp": 1683849600, "utcOffset": -4, "speed": 7.47594, "direction": 225.57183, "directionType": "Cross-shore", "gust": 20.21599, "optimalScore": 0}, {"timestamp": 1683853200, "utcOffset": -4, "speed": 7.53961, "direction": 237.24723, "directionType": "Cross-shore", "gust": 23.52053, "optimalScore": 0}, {"timestamp": 1683856800, "utcOffset": -4, "speed": 6.2859, "direction": 243.41697, "directionType": "Cross-shore", "gust": 17.88338, "optimalScore": 0}, {"timestamp": 1683860400, "utcOffset": -4, "speed": 5.28474, "direction": 243.12133, "directionType": "Cross-shore", "gust": 13.8013, "optimalScore": 0}, {"timestamp": 1683864000, "utcOffset": -4, "speed": 4.62188, "direction": 242.34881, "directionType": "Cross-shore", "gust": 9.52484, "optimalScore": 2}, {"timestamp": 1683867600, "utcOffset": -4, "speed": 4.81463, "direction": 245.16452, "directionType": "Cross-shore", "gust": 10.108, "optimalScore": 2}, {"timestamp": 1683871200, "utcOffset": -4, "speed": 4.24132, "direction": 241.91532, "directionType": "Cross-shore", "gust": 9.33046, "optimalScore": 2}, {"timestamp": 1683874800, "utcOffset": -4, "speed": 4.30006, "direction": 242.60837, "directionType": "Cross-shore", "gust": 4.30006, "optimalScore": 2}, {"timestamp": 1683878400, "utcOffset": -4, "speed": 4.40506, "direction": 246.88061, "directionType": "Cross-shore", "gust": 4.40506, "optimalScore": 2}, {"timestamp": 1683882000, "utcOffset": -4, "speed": 4.24555, "direction": 245.8793, "directionType": "Cross-shore", "gust": 4.24555, "optimalScore": 2}, {"timestamp": 1683885600, "utcOffset": -4, "speed": 4.08922, "direction": 251.68095, "directionType": "Cross-shore", "gust": 4.08922, "optimalScore": 2}, {"timestamp": 1683889200, "utcOffset": -4, "speed": 3.78601, "direction": 234.93244, "directionType": "Cross-shore", "gust": 3.78601, "optimalScore": 2}, {"timestamp": 1683892800, "utcOffset": -4, "speed": 3.83837, "direction": 231.54384, "directionType": "Cross-shore", "gust": 10.108, "optimalScore": 2}, {"timestamp": 1683896400, "utcOffset": -4, "speed": 4.62131, "direction": 215.49796, "directionType": "Cross-shore", "gust": 12.24623, "optimalScore": 2}, {"timestamp": 1683900000, "utcOffset": -4, "speed": 5.46949, "direction": 212.23227, "directionType": "Cross-shore", "gust": 15.55076, "optimalScore": 0}, {"timestamp": 1683903600, "utcOffset": -4, "speed": 6.31921, "direction": 315.46239, "directionType": "Offshore", "gust": 13.41253, "optimalScore": 0}, {"timestamp": 1683907200, "utcOffset": -4, "speed": 4.40615, "direction": 174.3457, "directionType": "Onshore", "gust": 4.40615, "optimalScore": 2}, {"timestamp": 1683910800, "utcOffset": -4, "speed": 7.11257, "direction": 187.17982, "directionType": "Onshore", "gust": 8.7473, "optimalScore": 0}, {"timestamp": 1683914400, "utcOffset": -4, "speed": 8.68751, "direction": 196.75907, "directionType": "Onshore", "gust": 14.77322, "optimalScore": 0}, {"timestamp": 1683918000, "utcOffset": -4, "speed": 9.36667, "direction": 204.95651, "directionType": "Onshore", "gust": 18.8553, "optimalScore": 0}, {"timestamp": 1683921600, "utcOffset": -4, "speed": 8.95128, "direction": 203.33707, "directionType": "Onshore", "gust": 20.41038, "optimalScore": 0}, {"timestamp": 1683925200, "utcOffset": -4, "speed": 8.02676, "direction": 206.91898, "directionType": "Cross-shore", "gust": 24.10368, "optimalScore": 0}, {"timestamp": 1683928800, "utcOffset": -4, "speed": 9.84521, "direction": 225.4432, "directionType": "Cross-shore", "gust": 32.07345, "optimalScore": 0}, {"timestamp": 1683932400, "utcOffset": -4, "speed": 10.64893, "direction": 222.55309, "directionType": "Cross-shore", "gust": 25.65876, "optimalScore": 0}, {"timestamp": 1683936000, "utcOffset": -4, "speed": 8.2066, "direction": 219.98949, "directionType": "Cross-shore", "gust": 23.52053, "optimalScore": 0}, {"timestamp": 1683939600, "utcOffset": -4, "speed": 7.74114, "direction": 219.06318, "directionType": "Cross-shore", "gust": 20.79914, "optimalScore": 0}, {"timestamp": 1683943200, "utcOffset": -4, "speed": 6.96647, "direction": 227.64156, "directionType": "Cross-shore", "gust": 21.57668, "optimalScore": 0}, {"timestamp": 1683946800, "utcOffset": -4, "speed": 6.08807, "direction": 238.34229, "directionType": "Cross-shore", "gust": 16.3283, "optimalScore": 0}, {"timestamp": 1683950400, "utcOffset": -4, "speed": 5.70962, "direction": 238.7807, "directionType": "Cross-shore", "gust": 16.91145, "optimalScore": 0}, {"timestamp": 1683954000, "utcOffset": -4, "speed": 5.63823, "direction": 235.56411, "directionType": "Cross-shore", "gust": 16.52268, "optimalScore": 0}, {"timestamp": 1683957600, "utcOffset": -4, "speed": 5.2479, "direction": 239.35484, "directionType": "Cross-shore", "gust": 9.71923, "optimalScore": 0}, {"timestamp": 1683961200, "utcOffset": -4, "speed": 5.18041, "direction": 236.56368, "directionType": "Cross-shore", "gust": 9.33046, "optimalScore": 0}, {"timestamp": 1683964800, "utcOffset": -4, "speed": 4.9813, "direction": 248.78287, "directionType": "Cross-shore", "gust": 9.52484, "optimalScore": 2}, {"timestamp": 1683968400, "utcOffset": -4, "speed": 3.82807, "direction": 267.53054, "directionType": "Offshore", "gust": 10.30238, "optimalScore": 2}, {"timestamp": 1683972000, "utcOffset": -4, "speed": 3.67232, "direction": 262.20544, "directionType": "Offshore", "gust": 10.88553, "optimalScore": 2}, {"timestamp": 1683975600, "utcOffset": -4, "speed": 3.62084, "direction": 291.85478, "directionType": "Offshore", "gust": 15.16199, "optimalScore": 2}, {"timestamp": 1683979200, "utcOffset": -4, "speed": 4.3043, "direction": 315.18698, "directionType": "Offshore", "gust": 14.77322, "optimalScore": 2}, {"timestamp": 1683982800, "utcOffset": -4, "speed": 5.12706, "direction": 319.36681, "directionType": "Offshore", "gust": 10.88553, "optimalScore": 0}, {"timestamp": 1683986400, "utcOffset": -4, "speed": 4.45062, "direction": 313.56376, "directionType": "Offshore", "gust": 13.02376, "optimalScore": 2}, {"timestamp": 1683990000, "utcOffset": -4, "speed": 5.11628, "direction": 293.01317, "directionType": "Offshore", "gust": 15.55076, "optimalScore": 0}, {"timestamp": 1683993600, "utcOffset": -4, "speed": 5.46723, "direction": 289.19027, "directionType": "Offshore", "gust": 13.99569, "optimalScore": 0}, {"timestamp": 1683997200, "utcOffset": -4, "speed": 4.84824, "direction": 286.71875, "directionType": "Offshore", "gust": 13.02376, "optimalScore": 2}, {"timestamp": 1684000800, "utcOffset": -4, "speed": 6.25267, "direction": 286.90748, "directionType": "Offshore", "gust": 11.66307, "optimalScore": 0}, {"timestamp": 1684004400, "utcOffset": -4, "speed": 5.38701, "direction": 259.67158, "directionType": "Offshore", "gust": 13.61971, "optimalScore": 0}, {"timestamp": 1684008000, "utcOffset": -4, "speed": 7.63397, "direction": 270.98614, "directionType": "Offshore", "gust": 14.011, "optimalScore": 0}, {"timestamp": 1684011600, "utcOffset": -4, "speed": 7.55177, "direction": 260.14691, "directionType": "Offshore", "gust": 13.824, "optimalScore": 0}, {"timestamp": 1684015200, "utcOffset": -4, "speed": 8.14473, "direction": 238.3166, "directionType": "Cross-shore", "gust": 17.13218, "optimalScore": 0}, {"timestamp": 1684018800, "utcOffset": -4, "speed": 6.33964, "direction": 242.44438, "directionType": "Cross-shore", "gust": 14.62875, "optimalScore": 0}, {"timestamp": 1684022400, "utcOffset": -4, "speed": 5.64677, "direction": 277.41061, "directionType": "Offshore", "gust": 18.50106, "optimalScore": 0}, {"timestamp": 1684026000, "utcOffset": -4, "speed": 6.59666, "direction": 326.33778, "directionType": "Offshore", "gust": 18.87493, "optimalScore": 0}, {"timestamp": 1684029600, "utcOffset": -4, "speed": 9.16658, "direction": 25.27761, "directionType": "Cross-shore", "gust": 20.037, "optimalScore": 0}, {"timestamp": 1684033200, "utcOffset": -4, "speed": 9.15883, "direction": 11.77156, "directionType": "Offshore", "gust": 22.75628, "optimalScore": 0}]}, "permissions": {"data": [], "violations": [{"code": 4001, "message": "User does not have optional permission:sl_premium-forecasts", "permission": {"name": "sl_premium-forecasts", "required": false}}, {"code": 4001, "message": "User does not have optional permission:sl_premium-cams", "permission": {"name": "sl_premium-cams", "required": false}}]}}