{"associated": {"units": {"temperature": "F", "tideHeight": "FT", "swellHeight": "FT", "waveHeight": "FT", "windSpeed": "KTS", "pressure": "MB"}, "utcOffset": -4, "location": {"lon": -70.79141, "lat": 42.9376373334092}, "forecastLocation": {"lon": -70.78551292419434, "lat": 42.93694613058707}, "offshoreLocation": {"lon": -70.75, "lat": 42.9}, "runInitializationTimestamp": 1681344000}, "data": {"wave": [{"timestamp": 1681358400, "probability": 100, "utcOffset": -4, "surf": {"min": 0, "max": 1, "optimalScore": 0, "plus": false, "humanRelation": "Shin to knee", "raw": {"min": 0.00171545454545452, "max": 0.7299545454545455}}, "swells": [{"height": 1.44357, "period": 10, "impact": 0.8291, "direction": 108.12, "directionMin": 103.87, "optimalScore": 0}, {"height": 0.3937, "period": 4, "impact": 0.1709, "direction": 19.44, "directionMin": 13.590000000000002, "optimalScore": 0}, {"height": 0, "period": 0, "impact": 0, "direction": 0, "directionMin": 0, "optimalScore": 0}, {"height": 0, "period": 0, "impact": 0, "direction": 0, "directionMin": 0, "optimalScore": 0}, {"height": 0, "period": 0, "impact": 0, "direction": 0, "directionMin": 0, "optimalScore": 0}, {"height": 0, "period": 0, "impact": 0, "direction": 0, "directionMin": 0, "optimalScore": 0}]}, {"timestamp": 1681362000, "probability": 100, "utcOffset": -4, "surf": {"min": 0, "max": 1, "optimalScore": 0, "plus": false, "humanRelation": "Shin to knee", "raw": {"min": -0.018513636363636232, "max": 0.6528836363636363}}, "swells": [{"height": 1.41076, "period": 9, "impact": 0.8258, "direction": 107.67, "directionMin": 103.435, "optimalScore": 0}, {"height": 0.3937, "period": 4, "impact": 0.1742, "direction": 20.31, "directionMin": 14.384999999999998, "optimalScore": 0}, {"height": 0, "period": 0, "impact": 0, "direction": 0, "directionMin": 0, "optimalScore": 0}, {"height": 0, "period": 0, "impact": 0, "direction": 0, "directionMin": 0, "optimalScore": 0}, {"height": 0, "period": 0, "impact": 0, "direction": 0, "directionMin": 0, "optimalScore": 0}, {"height": 0, "period": 0, "impact": 0, "direction": 0, "directionMin": 0, "optimalScore": 0}]}, {"timestamp": 1681365600, "probability": 100, "utcOffset": -4, "surf": {"min": 0, "max": 1, "optimalScore": 0, "plus": false, "humanRelation": "Shin to knee", "raw": {"min": 0.02924727272727279, "max": 0.6820527272727273}}, "swells": [{"height": 1.41076, "period": 9, "impact": 0.8407, "direction": 107.21, "directionMin": 102.97, "optimalScore": 0}, {"height": 0.36089, "period": 4, "impact": 0.1593, "direction": 21.09, "directionMin": 15.004999999999999, "optimalScore": 0}, {"height": 0, "period": 0, "impact": 0, "direction": 0, "directionMin": 0, "optimalScore": 0}, {"height": 0, "period": 0, "impact": 0, "direction": 0, "directionMin": 0, "optimalScore": 0}, {"height": 0, "period": 0, "impact": 0, "direction": 0, "directionMin": 0, "optimalScore": 0}, {"height": 0, "period": 0, "impact": 0, "direction": 0, "directionMin": 0, "optimalScore": 0}]}, {"timestamp": 1681369200, "probability": 100, "utcOffset": -4, "surf": {"min": 0, "max": 1, "optimalScore": 0, "plus": false, "humanRelation": "Shin to knee", "raw": {"min": 0.03385818181818179, "max": 0.643811818181818}}, "swells": [{"height": 1.41076, "period": 9, "impact": 0.8516, "direction": 106.78, "directionMin": 102.505, "optimalScore": 0}, {"height": 0.32808, "period": 4, "impact": 0.1484, "direction": 22.04, "directionMin": 15.68, "optimalScore": 0}, {"height": 0, "period": 0, "impact": 0, "direction": 0, "directionMin": 0, "optimalScore": 0}, {"height": 0, "period": 0, "impact": 0, "direction": 0, "directionMin": 0, "optimalScore": 0}, {"height": 0, "period": 0, "impact": 0, "direction": 0, "directionMin": 0, "optimalScore": 0}, {"height": 0, "period": 0, "impact": 0, "direction": 0, "directionMin": 0, "optimalScore": 0}]}, {"timestamp": 1681372800, "probability": 100, "utcOffset": -4, "surf": {"min": 0, "max": 1, "optimalScore": 0, "plus": false, "humanRelation": "Shin to knee", "raw": {"min": 0.01728909090909081, "max": 0.572460909090909}}, "swells": [{"height": 1.37795, "period": 9, "impact": 0.8465, "direction": 106.36, "directionMin": 102.035, "optimalScore": 0}, {"height": 0.32808, "period": 4, "impact": 0.1535, "direction": 23.26, "directionMin": 16.470000000000002, "optimalScore": 0}, {"height": 0, "period": 0, "impact": 0, "direction": 0, "directionMin": 0, "optimalScore": 0}, {"height": 0, "period": 0, "impact": 0, "direction": 0, "directionMin": 0, "optimalScore": 0}, {"height": 0, "period": 0, "impact": 0, "direction": 0, "directionMin": 0, "optimalScore": 0}, {"height": 0, "period": 0, "impact": 0, "direction": 0, "directionMin": 0, "optimalScore": 0}]}, {"timestamp": 1681376400, "probability": 100, "utcOffset": -4, "surf": {"min": 0, "max": 0, "optimalScore": 0, "plus": false, "humanRelation": "Flat", "raw": {"min": 0, "max": 0.5}}, "swells": [{"height": 1.34514, "period": 9, "impact": 0.8575, "direction": 105.96, "directionMin": 101.53999999999999, "optimalScore": 0}, {"height": 0.29528, "period": 4, "impact": 0.1425, "direction": 25.01, "directionMin": 17.73, "optimalScore": 0}, {"height": 0, "period": 0, "impact": 0, "direction": 0, "directionMin": 0, "optimalScore": 0}, {"height": 0, "period": 0, "impact": 0, "direction": 0, "directionMin": 0, "optimalScore": 0}, {"height": 0, "period": 0, "impact": 0, "direction": 0, "directionMin": 0, "optimalScore": 0}, {"height": 0, "period": 0, "impact": 0, "direction": 0, "directionMin": 0, "optimalScore": 0}]}, {"timestamp": 1681380000, "probability": 100, "utcOffset": -4, "surf": {"min": 0, "max": 1, "optimalScore": 0, "plus": false, "humanRelation": "Shin to knee", "raw": {"min": 0, "max": 1}}, "swells": [{"height": 1.34514, "period": 9, "impact": 1, "direction": 103.47, "directionMin": 95.275, "optimalScore": 0}, {"height": 0, "period": 0, "impact": 0, "direction": 0, "directionMin": 0, "optimalScore": 0}, {"height": 0, "period": 0, "impact": 0, "direction": 0, "directionMin": 0, "optimalScore": 0}, {"height": 0, "period": 0, "impact": 0, "direction": 0, "directionMin": 0, "optimalScore": 0}, {"height": 0, "period": 0, "impact": 0, "direction": 0, "directionMin": 0, "optimalScore": 0}, {"height": 0, "period": 0, "impact": 0, "direction": 0, "directionMin": 0, "optimalScore": 0}]}, {"timestamp": 1681383600, "probability": 100, "utcOffset": -4, "surf": {"min": 0, "max": 1, "optimalScore": 0, "plus": false, "humanRelation": "Shin to knee", "raw": {"min": -0.013506666666666778, "max": 0.9789033333333333}}, "swells": [{"height": 1.31234, "period": 9, "impact": 0.8411, "direction": 105.17, "directionMin": 100.58500000000001, "optimalScore": 0}, {"height": 0.26247, "period": 5, "impact": 0.1589, "direction": 31.44, "directionMin": 22.47, "optimalScore": 0}, {"height": 0, "period": 0, "impact": 0, "direction": 0, "directionMin": 0, "optimalScore": 0}, {"height": 0, "period": 0, "impact": 0, "direction": 0, "directionMin": 0, "optimalScore": 0}, {"height": 0, "period": 0, "impact": 0, "direction": 0, "directionMin": 0, "optimalScore": 0}, {"height": 0, "period": 0, "impact": 0, "direction": 0, "directionMin": 0, "optimalScore": 0}]}, {"timestamp": 1681387200, "probability": 100, "utcOffset": -4, "surf": {"min": 0, "max": 1, "optimalScore": 0, "plus": false, "humanRelation": "Shin to knee", "raw": {"min": -0.026503333333333323, "max": 0.9585966666666667}}, "swells": [{"height": 1.27953, "period": 9, "impact": 0.8451, "direction": 104.73, "directionMin": 100.035, "optimalScore": 0}, {"height": 0.22966, "period": 5, "impact": 0.1549, "direction": 35.68, "directionMin": 24.744999999999997, "optimalScore": 0}, {"height": 0, "period": 0, "impact": 0, "direction": 0, "directionMin": 0, "optimalScore": 0}, {"height": 0, "period": 0, "impact": 0, "direction": 0, "directionMin": 0, "optimalScore": 0}, {"height": 0, "period": 0, "impact": 0, "direction": 0, "directionMin": 0, "optimalScore": 0}, {"height": 0, "period": 0, "impact": 0, "direction": 0, "directionMin": 0, "optimalScore": 0}]}, {"timestamp": 1681390800, "probability": 100, "utcOffset": -4, "surf": {"min": 0, "max": 1, "optimalScore": 0, "plus": false, "humanRelation": "Shin to knee", "raw": {"min": -0.016079999999999872, "max": 0.9748700000000001}}, "swells": [{"height": 1.27953, "period": 9, "impact": 0.8359, "direction": 104.28, "directionMin": 99.47, "optimalScore": 0}, {"height": 0, "period": 0, "impact": 0, "direction": 0, "directionMin": 0, "optimalScore": 0}, {"height": 0.22966, "period": 5, "impact": 0.1641, "direction": 50.08, "directionMin": 31.485, "optimalScore": 0}, {"height": 0, "period": 0, "impact": 0, "direction": 0, "directionMin": 0, "optimalScore": 0}, {"height": 0, "period": 0, "impact": 0, "direction": 0, "directionMin": 0, "optimalScore": 0}, {"height": 0, "period": 0, "impact": 0, "direction": 0, "directionMin": 0, "optimalScore": 0}]}, {"timestamp": 1681394400, "probability": 100, "utcOffset": -4, "surf": {"min": 0, "max": 1, "optimalScore": 0, "plus": false, "humanRelation": "Shin to knee", "raw": {"min": -0.0286266666666668, "max": 0.9552733333333333}}, "swells": [{"height": 1.24672, "period": 9, "impact": 0.7633, "direction": 103.64, "directionMin": 98.905, "optimalScore": 0}, {"height": 0.19685, "period": 5, "impact": 0.1272, "direction": 36.37, "directionMin": 29.729999999999997, "optimalScore": 0}, {"height": 0, "period": 0, "impact": 0, "direction": 0, "directionMin": 0, "optimalScore": 0}, {"height": 0.32808, "period": 3, "impact": 0.1095, "direction": 116.17, "directionMin": 104.765, "optimalScore": 0}, {"height": 0, "period": 0, "impact": 0, "direction": 0, "directionMin": 0, "optimalScore": 0}, {"height": 0, "period": 0, "impact": 0, "direction": 0, "directionMin": 0, "optimalScore": 0}]}, {"timestamp": 1681398000, "probability": 100, "utcOffset": -4, "surf": {"min": 0, "max": 1, "optimalScore": 0, "plus": false, "humanRelation": "Shin to knee", "raw": {"min": -0.01822333333333348, "max": 0.9715366666666668}}, "swells": [{"height": 1.24672, "period": 9, "impact": 0.8276, "direction": 102.79, "directionMin": 97.65, "optimalScore": 0}, {"height": 0, "period": 0, "impact": 0, "direction": 0, "directionMin": 0, "optimalScore": 0}, {"height": 0, "period": 0, "impact": 0, "direction": 0, "directionMin": 0, "optimalScore": 0}, {"height": 0.45932, "period": 3, "impact": 0.1724, "direction": 112.41, "directionMin": 97.705, "optimalScore": 0}, {"height": 0, "period": 0, "impact": 0, "direction": 0, "directionMin": 0, "optimalScore": 0}, {"height": 0, "period": 0, "impact": 0, "direction": 0, "directionMin": 0, "optimalScore": 0}]}, {"timestamp": 1681401600, "probability": 100, "utcOffset": -4, "surf": {"min": 0, "max": 1, "optimalScore": 0, "plus": false, "humanRelation": "Shin to knee", "raw": {"min": 0, "max": 1}}, "swells": [{"height": 1.21391, "period": 9, "impact": 0.8112, "direction": 102.33, "directionMin": 97.375, "optimalScore": 0}, {"height": 0, "period": 0, "impact": 0, "direction": 0, "directionMin": 0, "optimalScore": 0}, {"height": 0, "period": 0, "impact": 0, "direction": 0, "directionMin": 0, "optimalScore": 0}, {"height": 0.52493, "period": 3, "impact": 0.1888, "direction": 116.57, "directionMin": 103.04499999999999, "optimalScore": 0}, {"height": 0, "period": 0, "impact": 0, "direction": 0, "directionMin": 0, "optimalScore": 0}, {"height": 0, "period": 0, "impact": 0, "direction": 0, "directionMin": 0, "optimalScore": 0}]}, {"timestamp": 1681405200, "probability": 100, "utcOffset": -4, "surf": {"min": 0, "max": 1, "optimalScore": 0, "plus": false, "humanRelation": "Shin to knee", "raw": {"min": 0.016663333333333474, "max": 0.9427116666666667}}, "swells": [{"height": 1.21391, "period": 9, "impact": 0.804, "direction": 101.96, "directionMin": 97.1, "optimalScore": 0}, {"height": 0, "period": 0, "impact": 0, "direction": 0, "directionMin": 0, "optimalScore": 0}, {"height": 0, "period": 0, "impact": 0, "direction": 0, "directionMin": 0, "optimalScore": 0}, {"height": 0.55774, "period": 3, "impact": 0.196, "direction": 119.09, "directionMin": 106.325, "optimalScore": 0}, {"height": 0, "period": 0, "impact": 0, "direction": 0, "directionMin": 0, "optimalScore": 0}, {"height": 0, "period": 0, "impact": 0, "direction": 0, "directionMin": 0, "optimalScore": 0}]}, {"timestamp": 1681408800, "probability": 100, "utcOffset": -4, "surf": {"min": 0, "max": 1, "optimalScore": 0, "plus": false, "humanRelation": "Shin to knee", "raw": {"min": 0.00884666666666667, "max": 0.8471633333333334}}, "swells": [{"height": 1.1811, "period": 9, "impact": 0.79, "direction": 101.58, "directionMin": 96.77, "optimalScore": 0}, {"height": 0, "period": 0, "impact": 0, "direction": 0, "directionMin": 0, "optimalScore": 0}, {"height": 0, "period": 0, "impact": 0, "direction": 0, "directionMin": 0, "optimalScore": 0}, {"height": 0.55774, "period": 3, "impact": 0.21, "direction": 120.57, "directionMin": 108.46499999999999, "optimalScore": 0}, {"height": 0, "period": 0, "impact": 0, "direction": 0, "directionMin": 0, "optimalScore": 0}, {"height": 0, "period": 0, "impact": 0, "direction": 0, "directionMin": 0, "optimalScore": 0}]}, {"timestamp": 1681412400, "probability": 100, "utcOffset": -4, "surf": {"min": 0, "max": 1, "optimalScore": 0, "plus": false, "humanRelation": "Shin to knee", "raw": {"min": 0.024950000000000028, "max": 0.788985}}, "swells": [{"height": 1.1811, "period": 9, "impact": 0.7982, "direction": 100.99, "directionMin": 95.78, "optimalScore": 0}, {"height": 0, "period": 0, "impact": 0, "direction": 0, "directionMin": 0, "optimalScore": 0}, {"height": 0, "period": 0, "impact": 0, "direction": 0, "directionMin": 0, "optimalScore": 0}, {"height": 0.55774, "period": 3, "impact": 0.2018, "direction": 122.63, "directionMin": 112.36999999999999, "optimalScore": 0}, {"height": 0, "period": 0, "impact": 0, "direction": 0, "directionMin": 0, "optimalScore": 0}, {"height": 0, "period": 0, "impact": 0, "direction": 0, "directionMin": 0, "optimalScore": 0}]}, {"timestamp": 1681416000, "probability": 100, "utcOffset": -4, "surf": {"min": 0, "max": 1, "optimalScore": 0, "plus": false, "humanRelation": "Shin to knee", "raw": {"min": 0.016503333333333314, "max": 0.6924566666666666}}, "swells": [{"height": 1.14829, "period": 9, "impact": 0.7934, "direction": 100.69, "directionMin": 95.57, "optimalScore": 0}, {"height": 0, "period": 0, "impact": 0, "direction": 0, "directionMin": 0, "optimalScore": 0}, {"height": 0, "period": 0, "impact": 0, "direction": 0, "directionMin": 0, "optimalScore": 0}, {"height": 0.55774, "period": 3, "impact": 0.2066, "direction": 123.07, "directionMin": 113.00999999999999, "optimalScore": 0}, {"height": 0, "period": 0, "impact": 0, "direction": 0, "directionMin": 0, "optimalScore": 0}, {"height": 0, "period": 0, "impact": 0, "direction": 0, "directionMin": 0, "optimalScore": 0}]}, {"timestamp": 1681419600, "probability": 100, "utcOffset": -4, "surf": {"min": 0, "max": 1, "optimalScore": 0, "plus": false, "humanRelation": "Shin to knee", "raw": {"min": -0.016173333333333373, "max": 0.5580683333333332}}, "swells": [{"height": 1.08268, "period": 9, "impact": 0.6756, "direction": 99.15, "directionMin": 95.32000000000001, "optimalScore": 0}, {"height": 0, "period": 0, "impact": 0, "direction": 0, "directionMin": 0, "optimalScore": 0}, {"height": 0, "period": 0, "impact": 0, "direction": 0, "directionMin": 0, "optimalScore": 0}, {"height": 0.55774, "period": 3, "impact": 0.1852, "direction": 123.41, "directionMin": 113.44, "optimalScore": 0}, {"height": 0.22966, "period": 8, "impact": 0.1392, "direction": 135.04, "directionMin": 132.045, "optimalScore": 0}, {"height": 0, "period": 0, "impact": 0, "direction": 0, "directionMin": 0, "optimalScore": 0}]}, {"timestamp": 1681423200, "probability": 93.44444444444446, "utcOffset": -4, "surf": {"min": 0, "max": 0, "optimalScore": 0, "plus": false, "humanRelation": "Flat", "raw": {"min": 0, "max": 0.5}}, "swells": [{"height": 1.08268, "period": 9, "impact": 0.69, "direction": 98.96, "directionMin": 95.11999999999999, "optimalScore": 0}, {"height": 0, "period": 0, "impact": 0, "direction": 0, "directionMin": 0, "optimalScore": 0}, {"height": 0, "period": 0, "impact": 0, "direction": 0, "directionMin": 0, "optimalScore": 0}, {"height": 0.52493, "period": 3, "impact": 0.1798, "direction": 123.4, "directionMin": 113.41000000000001, "optimalScore": 0}, {"height": 0.19685, "period": 8, "impact": 0.1302, "direction": 135.39, "directionMin": 132.36999999999998, "optimalScore": 0}, {"height": 0, "period": 0, "impact": 0, "direction": 0, "directionMin": 0, "optimalScore": 0}]}, {"timestamp": 1681426800, "probability": 93.44444444444446, "utcOffset": -4, "surf": {"min": 0, "max": 1, "optimalScore": 0, "plus": false, "humanRelation": "Shin to knee", "raw": {"min": 0.008078333333333299, "max": 0.5126241666666667}}, "swells": [{"height": 1.04987, "period": 9, "impact": 0.6762, "direction": 98.71, "directionMin": 94.895, "optimalScore": 0}, {"height": 0, "period": 0, "impact": 0, "direction": 0, "directionMin": 0, "optimalScore": 0}, {"height": 0, "period": 0, "impact": 0, "direction": 0, "directionMin": 0, "optimalScore": 0}, {"height": 0.52493, "period": 3, "impact": 0.1805, "direction": 123.09, "directionMin": 113.04, "optimalScore": 0}, {"height": 0.22966, "period": 8, "impact": 0.1433, "direction": 135.39, "directionMin": 132.36999999999998, "optimalScore": 0}, {"height": 0, "period": 0, "impact": 0, "direction": 0, "directionMin": 0, "optimalScore": 0}]}, {"timestamp": 1681430400, "probability": 93.44444444444446, "utcOffset": -4, "surf": {"min": 0, "max": 1, "optimalScore": 0, "plus": false, "humanRelation": "Shin to knee", "raw": {"min": 0.015056666666666607, "max": 0.5235383333333332}}, "swells": [{"height": 1.01706, "period": 9, "impact": 0.7935, "direction": 100, "directionMin": 94.695, "optimalScore": 0}, {"height": 0, "period": 0, "impact": 0, "direction": 0, "directionMin": 0, "optimalScore": 0}, {"height": 0, "period": 0, "impact": 0, "direction": 0, "directionMin": 0, "optimalScore": 0}, {"height": 0.49213, "period": 3, "impact": 0.2065, "direction": 122.73, "directionMin": 112.64, "optimalScore": 0}, {"height": 0, "period": 0, "impact": 0, "direction": 0, "directionMin": 0, "optimalScore": 0}, {"height": 0, "period": 0, "impact": 0, "direction": 0, "directionMin": 0, "optimalScore": 0}]}, {"timestamp": 1681434000, "probability": 71.55555555555556, "utcOffset": -4, "surf": {"min": 0, "max": 0, "optimalScore": 0, "plus": false, "humanRelation": "Flat", "raw": {"min": -0.001495000000000024, "max": 0.4976624999999999}}, "swells": [{"height": 0.95144, "period": 9, "impact": 0.665, "direction": 98.15, "directionMin": 94.39500000000001, "optimalScore": 0}, {"height": 0, "period": 0, "impact": 0, "direction": 0, "directionMin": 0, "optimalScore": 0}, {"height": 0, "period": 0, "impact": 0, "direction": 0, "directionMin": 0, "optimalScore": 0}, {"height": 0.45932, "period": 3, "impact": 0.1824, "direction": 122.4, "directionMin": 112.28, "optimalScore": 0}, {"height": 0.22966, "period": 8, "impact": 0.1525, "direction": 135.1, "directionMin": 132.085, "optimalScore": 0}, {"height": 0, "period": 0, "impact": 0, "direction": 0, "directionMin": 0, "optimalScore": 0}]}, {"timestamp": 1681437600, "probability": null, "utcOffset": -4, "surf": {"min": 0, "max": 1, "optimalScore": 0, "plus": false, "humanRelation": "Shin to knee", "raw": {"min": 0.0058633333333332205, "max": 0.5091566666666666}}, "swells": [{"height": 0.91864, "period": 9, "impact": 0.6588, "direction": 97.94, "directionMin": 94.125, "optimalScore": 0}, {"height": 0, "period": 0, "impact": 0, "direction": 0, "directionMin": 0, "optimalScore": 0}, {"height": 0, "period": 0, "impact": 0, "direction": 0, "directionMin": 0, "optimalScore": 0}, {"height": 0.45932, "period": 3, "impact": 0.1858, "direction": 122.21, "directionMin": 111.925, "optimalScore": 0}, {"height": 0.22966, "period": 8, "impact": 0.1554, "direction": 135.21, "directionMin": 132.185, "optimalScore": 0}, {"height": 0, "period": 0, "impact": 0, "direction": 0, "directionMin": 0, "optimalScore": 0}]}, {"timestamp": 1681441200, "probability": null, "utcOffset": -4, "surf": {"min": 0, "max": 1, "optimalScore": 0, "plus": false, "humanRelation": "Shin to knee", "raw": {"min": 0.013181666666666647, "max": 0.5206008333333332}}, "swells": [{"height": 0.88583, "period": 9, "impact": 0.6598, "direction": 97.79, "directionMin": 93.81500000000001, "optimalScore": 0}, {"height": 0, "period": 0, "impact": 0, "direction": 0, "directionMin": 0, "optimalScore": 0}, {"height": 0, "period": 0, "impact": 0, "direction": 0, "directionMin": 0, "optimalScore": 0}, {"height": 0.42651, "period": 3, "impact": 0.1799, "direction": 122.25, "directionMin": 111.615, "optimalScore": 0}, {"height": 0.22966, "period": 8, "impact": 0.1603, "direction": 135.41, "directionMin": 132.35999999999999, "optimalScore": 0}, {"height": 0, "period": 0, "impact": 0, "direction": 0, "directionMin": 0, "optimalScore": 0}]}]}, "permissions": {"data": [], "violations": [{"code": 4001, "message": "User does not have optional permission:sl_premium-forecasts", "permission": {"name": "sl_premium-forecasts", "required": false}}, {"code": 4001, "message": "User does not have optional permission:sl_premium-cams", "permission": {"name": "sl_premium-cams", "required": false}}]}}