{"associated": {"units": {"temperature": "F", "tideHeight": "FT", "swellHeight": "FT", "waveHeight": "FT", "windSpeed": "KTS", "pressure": "MB"}, "utcOffset": -4, "location": {"lon": -70.79141, "lat": 42.9376373334092}, "forecastLocation": {"lon": -70.78551292419434, "lat": 42.93694613058707}, "offshoreLocation": {"lon": -70.75, "lat": 42.9}, "runInitializationTimestamp": 1687759200}, "data": {"wave": [{"timestamp": 1687752000, "probability": 76.66666666666667, "utcOffset": -4, "surf": {"min": 0, "max": 1, "optimalScore": 0, "plus": false, "humanRelation": "Shin to knee", "raw": {"min": -0.10825599999999991, "max": 0.8308420000000001}}, "power": 1.40201, "swells": [{"height": 1.67323, "period": 8, "impact": 0.5692, "power": 0.99661, "direction": 127.3, "directionMin": 120.895, "optimalScore": 0}, {"height": 0.91864, "period": 11, "impact": 0.4308, "power": 0.4054, "direction": 121.6, "directionMin": 116.55, "optimalScore": 0}, {"height": 0, "period": 0, "impact": 0, "power": 0, "direction": 0, "directionMin": 0, "optimalScore": 0}, {"height": 0, "period": 0, "impact": 0, "power": 0, "direction": 0, "directionMin": 0, "optimalScore": 0}, {"height": 0, "period": 0, "impact": 0, "power": 0, "direction": 0, "directionMin": 0, "optimalScore": 0}, {"height": 0, "period": 0, "impact": 0, "power": 0, "direction": 0, "directionMin": 0, "optimalScore": 0}]}, {"timestamp": 1687755600, "probability": 76.66666666666667, "utcOffset": -4, "surf": {"min": 0, "max": 1, "optimalScore": 0, "plus": false, "humanRelation": "Shin to knee", "raw": {"min": -0.1898620000000001, "max": 0.7033440000000001}}, "power": 1.45154, "swells": [{"height": 1.5748, "period": 7, "impact": 0.4871, "power": 0.8229, "direction": 128.38, "directionMin": 121.74499999999999, "optimalScore": 0}, {"height": 1.14829, "period": 10, "impact": 0.5129, "power": 0.62864, "direction": 121.45, "directionMin": 116.625, "optimalScore": 0}, {"height": 0, "period": 0, "impact": 0, "power": 0, "direction": 0, "directionMin": 0, "optimalScore": 0}, {"height": 0, "period": 0, "impact": 0, "power": 0, "direction": 0, "directionMin": 0, "optimalScore": 0}, {"height": 0, "period": 0, "impact": 0, "power": 0, "direction": 0, "directionMin": 0, "optimalScore": 0}, {"height": 0, "period": 0, "impact": 0, "power": 0, "direction": 0, "directionMin": 0, "optimalScore": 0}]}, {"timestamp": 1687759200, "probability": 76.66666666666667, "utcOffset": -4, "surf": {"min": 0, "max": 1, "optimalScore": 0, "plus": false, "humanRelation": "Shin to knee", "raw": {"min": -0.1836080000000001, "max": 0.713126}}, "power": 1.44971, "swells": [{"height": 1.64042, "period": 7, "impact": 0.5096, "power": 0.89781, "direction": 127.94, "directionMin": 121.285, "optimalScore": 0}, {"height": 1.08268, "period": 10, "impact": 0.4904, "power": 0.5519, "direction": 121.68, "directionMin": 116.61500000000001, "optimalScore": 0}, {"height": 0, "period": 0, "impact": 0, "power": 0, "direction": 0, "directionMin": 0, "optimalScore": 0}, {"height": 0, "period": 0, "impact": 0, "power": 0, "direction": 0, "directionMin": 0, "optimalScore": 0}, {"height": 0, "period": 0, "impact": 0, "power": 0, "direction": 0, "directionMin": 0, "optimalScore": 0}, {"height": 0, "period": 0, "impact": 0, "power": 0, "direction": 0, "directionMin": 0, "optimalScore": 0}]}, {"timestamp": 1687762800, "probability": 50, "utcOffset": -4, "surf": {"min": 0, "max": 1, "optimalScore": 0, "plus": false, "humanRelation": "Shin to knee", "raw": {"min": -0.203534, "max": 0.6819780000000002}}, "power": 1.30103, "swells": [{"height": 1.21391, "period": 7, "impact": 0.3318, "power": 0.49164, "direction": 128.33, "directionMin": 123.42500000000001, "optimalScore": 0}, {"height": 1.08268, "period": 10, "impact": 0.4055, "power": 0.54495, "direction": 121.62, "directionMin": 116.52000000000001, "optimalScore": 0}, {"height": 1.14829, "period": 4, "impact": 0.2627, "power": 0.26444, "direction": 127.48, "directionMin": 119.11500000000001, "optimalScore": 0}, {"height": 0, "period": 0, "impact": 0, "power": 0, "direction": 0, "directionMin": 0, "optimalScore": 0}, {"height": 0, "period": 0, "impact": 0, "power": 0, "direction": 0, "directionMin": 0, "optimalScore": 0}, {"height": 0, "period": 0, "impact": 0, "power": 0, "direction": 0, "directionMin": 0, "optimalScore": 0}]}, {"timestamp": 1687766400, "probability": 50, "utcOffset": -4, "surf": {"min": 0, "max": 1, "optimalScore": 0, "plus": false, "humanRelation": "Shin to knee", "raw": {"min": 0, "max": 1}}, "power": 1.45257, "swells": [{"height": 1.73885, "period": 8, "impact": 0.5771, "power": 1.05563, "direction": 127.02, "directionMin": 120.34, "optimalScore": 0}, {"height": 0.91864, "period": 10, "impact": 0.4229, "power": 0.39694, "direction": 122.46, "directionMin": 117.17999999999999, "optimalScore": 0}, {"height": 0, "period": 0, "impact": 0, "power": 0, "direction": 0, "directionMin": 0, "optimalScore": 0}, {"height": 0, "period": 0, "impact": 0, "power": 0, "direction": 0, "directionMin": 0, "optimalScore": 0}, {"height": 0, "period": 0, "impact": 0, "power": 0, "direction": 0, "directionMin": 0, "optimalScore": 0}, {"height": 0, "period": 0, "impact": 0, "power": 0, "direction": 0, "directionMin": 0, "optimalScore": 0}]}, {"timestamp": 1687770000, "probability": 50, "utcOffset": -4, "surf": {"min": 0, "max": 1, "optimalScore": 0, "plus": false, "humanRelation": "Shin to knee", "raw": {"min": 0, "max": 1}}, "power": 1.39745, "swells": [{"height": 1.67323, "period": 8, "impact": 0.5637, "power": 0.97619, "direction": 127.13, "directionMin": 120.42, "optimalScore": 0}, {"height": 0.95144, "period": 10, "impact": 0.4363, "power": 0.42126, "direction": 121.87, "directionMin": 116.99000000000001, "optimalScore": 0}, {"height": 0, "period": 0, "impact": 0, "power": 0, "direction": 0, "directionMin": 0, "optimalScore": 0}, {"height": 0, "period": 0, "impact": 0, "power": 0, "direction": 0, "directionMin": 0, "optimalScore": 0}, {"height": 0, "period": 0, "impact": 0, "power": 0, "direction": 0, "directionMin": 0, "optimalScore": 0}, {"height": 0, "period": 0, "impact": 0, "power": 0, "direction": 0, "directionMin": 0, "optimalScore": 0}]}, {"timestamp": 1687773600, "probability": 80, "utcOffset": -4, "surf": {"min": 0, "max": 1, "optimalScore": 0, "plus": false, "humanRelation": "Shin to knee", "raw": {"min": 0, "max": 1}}, "power": 1.37044, "swells": [{"height": 1.67323, "period": 8, "impact": 0.5701, "power": 0.97619, "direction": 126.95, "directionMin": 120.42, "optimalScore": 0}, {"height": 0.91864, "period": 10, "impact": 0.4299, "power": 0.39425, "direction": 121.16, "directionMin": 116.17999999999999, "optimalScore": 0}, {"height": 0, "period": 0, "impact": 0, "power": 0, "direction": 0, "directionMin": 0, "optimalScore": 0}, {"height": 0, "period": 0, "impact": 0, "power": 0, "direction": 0, "directionMin": 0, "optimalScore": 0}, {"height": 0, "period": 0, "impact": 0, "power": 0, "direction": 0, "directionMin": 0, "optimalScore": 0}, {"height": 0, "period": 0, "impact": 0, "power": 0, "direction": 0, "directionMin": 0, "optimalScore": 0}]}, {"timestamp": 1687777200, "probability": 80, "utcOffset": -4, "surf": {"min": 0, "max": 1, "optimalScore": 0, "plus": false, "humanRelation": "Shin to knee", "raw": {"min": 0, "max": 1}}, "power": 1.32854, "swells": [{"height": 1.64042, "period": 8, "impact": 0.5663, "power": 0.93583, "direction": 126.68, "directionMin": 120.22000000000001, "optimalScore": 0}, {"height": 0.91864, "period": 10, "impact": 0.4337, "power": 0.39271, "direction": 121.42, "directionMin": 116.44, "optimalScore": 0}, {"height": 0, "period": 0, "impact": 0, "power": 0, "direction": 0, "directionMin": 0, "optimalScore": 0}, {"height": 0, "period": 0, "impact": 0, "power": 0, "direction": 0, "directionMin": 0, "optimalScore": 0}, {"height": 0, "period": 0, "impact": 0, "power": 0, "direction": 0, "directionMin": 0, "optimalScore": 0}, {"height": 0, "period": 0, "impact": 0, "power": 0, "direction": 0, "directionMin": 0, "optimalScore": 0}]}, {"timestamp": 1687780800, "probability": 80, "utcOffset": -4, "surf": {"min": 1, "max": 2, "optimalScore": 0, "plus": false, "humanRelation": "Knee to thigh", "raw": {"min": 0.008227499999999832, "max": 1.0128475}}, "power": 1.32494, "swells": [{"height": 1.64042, "period": 8, "impact": 0.5664, "power": 0.93338, "direction": 126.48, "directionMin": 120.08500000000001, "optimalScore": 0}, {"height": 0.91864, "period": 10, "impact": 0.4336, "power": 0.39156, "direction": 121.7, "directionMin": 116.69, "optimalScore": 0}, {"height": 0, "period": 0, "impact": 0, "power": 0, "direction": 0, "directionMin": 0, "optimalScore": 0}, {"height": 0, "period": 0, "impact": 0, "power": 0, "direction": 0, "directionMin": 0, "optimalScore": 0}, {"height": 0, "period": 0, "impact": 0, "power": 0, "direction": 0, "directionMin": 0, "optimalScore": 0}, {"height": 0, "period": 0, "impact": 0, "power": 0, "direction": 0, "directionMin": 0, "optimalScore": 0}]}, {"timestamp": 1687784400, "probability": 53.33333333333334, "utcOffset": -4, "surf": {"min": 0, "max": 1, "optimalScore": 0, "plus": false, "humanRelation": "Shin to knee", "raw": {"min": -0.017185000000000117, "max": 0.9731449999999999}}, "power": 1.27466, "swells": [{"height": 1.5748, "period": 8, "impact": 0.5661, "power": 0.85794, "direction": 126.19, "directionMin": 119.75, "optimalScore": 0}, {"height": 0.95144, "period": 10, "impact": 0.4339, "power": 0.41672, "direction": 122.68, "directionMin": 117.77000000000001, "optimalScore": 0}, {"height": 0, "period": 0, "impact": 0, "power": 0, "direction": 0, "directionMin": 0, "optimalScore": 0}, {"height": 0, "period": 0, "impact": 0, "power": 0, "direction": 0, "directionMin": 0, "optimalScore": 0}, {"height": 0, "period": 0, "impact": 0, "power": 0, "direction": 0, "directionMin": 0, "optimalScore": 0}, {"height": 0, "period": 0, "impact": 0, "power": 0, "direction": 0, "directionMin": 0, "optimalScore": 0}]}, {"timestamp": 1687788000, "probability": 53.33333333333334, "utcOffset": -4, "surf": {"min": 0, "max": 1, "optimalScore": 0, "plus": false, "humanRelation": "Shin to knee", "raw": {"min": -0.008267500000000094, "max": 0.9870825000000001}}, "power": 1.27271, "swells": [{"height": 1.5748, "period": 8, "impact": 0.5662, "power": 0.85681, "direction": 126.07, "directionMin": 119.66499999999999, "optimalScore": 0}, {"height": 0.95144, "period": 10, "impact": 0.4338, "power": 0.4159, "direction": 122.96, "directionMin": 118.05, "optimalScore": 0}, {"height": 0, "period": 0, "impact": 0, "power": 0, "direction": 0, "directionMin": 0, "optimalScore": 0}, {"height": 0, "period": 0, "impact": 0, "power": 0, "direction": 0, "directionMin": 0, "optimalScore": 0}, {"height": 0, "period": 0, "impact": 0, "power": 0, "direction": 0, "directionMin": 0, "optimalScore": 0}, {"height": 0, "period": 0, "impact": 0, "power": 0, "direction": 0, "directionMin": 0, "optimalScore": 0}]}, {"timestamp": 1687791600, "probability": 53.33333333333334, "utcOffset": -4, "surf": {"min": 0, "max": 1, "optimalScore": 0, "plus": false, "humanRelation": "Shin to knee", "raw": {"min": 0, "max": 1}}, "power": 1.26962, "swells": [{"height": 1.5748, "period": 8, "impact": 0.5661, "power": 0.85455, "direction": 125.85, "directionMin": 119.30499999999999, "optimalScore": 0}, {"height": 0.95144, "period": 10, "impact": 0.4339, "power": 0.41507, "direction": 123.03, "directionMin": 118.115, "optimalScore": 0}, {"height": 0, "period": 0, "impact": 0, "power": 0, "direction": 0, "directionMin": 0, "optimalScore": 0}, {"height": 0, "period": 0, "impact": 0, "power": 0, "direction": 0, "directionMin": 0, "optimalScore": 0}, {"height": 0, "period": 0, "impact": 0, "power": 0, "direction": 0, "directionMin": 0, "optimalScore": 0}, {"height": 0, "period": 0, "impact": 0, "power": 0, "direction": 0, "directionMin": 0, "optimalScore": 0}]}, {"timestamp": 1687795200, "probability": 96.66666666666669, "utcOffset": -4, "surf": {"min": 1, "max": 2, "optimalScore": 2, "plus": false, "humanRelation": "Knee to thigh", "raw": {"min": 1, "max": 2}}, "power": 1.3036, "swells": [{"height": 1.60761, "period": 8, "impact": 0.5703, "power": 0.88935, "direction": 124.99, "directionMin": 117.445, "optimalScore": 0}, {"height": 0.95144, "period": 10, "impact": 0.4297, "power": 0.41425, "direction": 123.1, "directionMin": 118.14999999999999, "optimalScore": 0}, {"height": 0, "period": 0, "impact": 0, "power": 0, "direction": 0, "directionMin": 0, "optimalScore": 0}, {"height": 0, "period": 0, "impact": 0, "power": 0, "direction": 0, "directionMin": 0, "optimalScore": 0}, {"height": 0, "period": 0, "impact": 0, "power": 0, "direction": 0, "directionMin": 0, "optimalScore": 0}, {"height": 0, "period": 0, "impact": 0, "power": 0, "direction": 0, "directionMin": 0, "optimalScore": 0}]}, {"timestamp": 1687798800, "probability": 96.66666666666669, "utcOffset": -4, "surf": {"min": 1, "max": 2, "optimalScore": 2, "plus": false, "humanRelation": "Knee to thigh", "raw": {"min": 1, "max": 2}}, "power": 1.29225, "swells": [{"height": 1.60761, "period": 8, "impact": 0.5059, "power": 0.88817, "direction": 126.28, "directionMin": 120.325, "optimalScore": 0}, {"height": 0.91864, "period": 10, "impact": 0.3934, "power": 0.38733, "direction": 122.24, "directionMin": 117.16, "optimalScore": 0}, {"height": 0, "period": 0, "impact": 0, "power": 0, "direction": 0, "directionMin": 0, "optimalScore": 0}, {"height": 0.42651, "period": 2, "impact": 0.1006, "power": 0.01675, "direction": 63.94, "directionMin": 54.675, "optimalScore": 0}, {"height": 0, "period": 0, "impact": 0, "power": 0, "direction": 0, "directionMin": 0, "optimalScore": 0}, {"height": 0, "period": 0, "impact": 0, "power": 0, "direction": 0, "directionMin": 0, "optimalScore": 0}]}, {"timestamp": 1687802400, "probability": 96.66666666666669, "utcOffset": -4, "surf": {"min": 1, "max": 2, "optimalScore": 0, "plus": false, "humanRelation": "Knee to thigh", "raw": {"min": 0.9226300000000001, "max": 1.9916140000000002}}, "power": 1.3846, "swells": [{"height": 1.70604, "period": 8, "impact": 0.5018, "power": 0.99893, "direction": 121.19, "directionMin": 110.33, "optimalScore": 0}, {"height": 0.88583, "period": 10, "impact": 0.3406, "power": 0.3598, "direction": 122.29, "directionMin": 117.27000000000001, "optimalScore": 0}, {"height": 0, "period": 0, "impact": 0, "power": 0, "direction": 0, "directionMin": 0, "optimalScore": 0}, {"height": 0, "period": 0, "impact": 0, "power": 0, "direction": 0, "directionMin": 0, "optimalScore": 0}, {"height": 0.19685, "period": 15, "impact": 0.1576, "power": 0.02587, "direction": 109.06, "directionMin": 105.06, "optimalScore": 0}, {"height": 0, "period": 0, "impact": 0, "power": 0, "direction": 0, "directionMin": 0, "optimalScore": 0}]}, {"timestamp": 1687806000, "probability": 100, "utcOffset": -4, "surf": {"min": 1, "max": 2, "optimalScore": 0, "plus": false, "humanRelation": "Knee to thigh", "raw": {"min": 0.6347200000000001, "max": 1.654258}}, "power": 1.34135, "swells": [{"height": 1.64042, "period": 8, "impact": 0.4217, "power": 0.92356, "direction": 125.88, "directionMin": 119.82499999999999, "optimalScore": 0}, {"height": 0.88583, "period": 10, "impact": 0.313, "power": 0.35908, "direction": 122.06, "directionMin": 117.02, "optimalScore": 0}, {"height": 0, "period": 0, "impact": 0, "power": 0, "direction": 0, "directionMin": 0, "optimalScore": 0}, {"height": 0.52493, "period": 3, "impact": 0.1206, "power": 0.03291, "direction": 58.66, "directionMin": 48.669999999999995, "optimalScore": 0}, {"height": 0.19685, "period": 15, "impact": 0.1447, "power": 0.0258, "direction": 109.99, "directionMin": 106.33, "optimalScore": 0}, {"height": 0, "period": 0, "impact": 0, "power": 0, "direction": 0, "directionMin": 0, "optimalScore": 0}]}, {"timestamp": 1687809600, "probability": 100, "utcOffset": -4, "surf": {"min": 1, "max": 2, "optimalScore": 0, "plus": false, "humanRelation": "Knee to thigh", "raw": {"min": 0.42735, "max": 1.442732}}, "power": 1.33033, "swells": [{"height": 1.60761, "period": 8, "impact": 0.4197, "power": 0.88699, "direction": 125.83, "directionMin": 119.765, "optimalScore": 0}, {"height": 0.91864, "period": 10, "impact": 0.3063, "power": 0.38233, "direction": 122.91, "directionMin": 118.00999999999999, "optimalScore": 0}, {"height": 0, "period": 0, "impact": 0, "power": 0, "direction": 0, "directionMin": 0, "optimalScore": 0}, {"height": 0.52493, "period": 3, "impact": 0.1274, "power": 0.03517, "direction": 58, "directionMin": 47.63, "optimalScore": 0}, {"height": 0.19685, "period": 15, "impact": 0.1466, "power": 0.02584, "direction": 109.97, "directionMin": 106.30499999999999, "optimalScore": 0}, {"height": 0, "period": 0, "impact": 0, "power": 0, "direction": 0, "directionMin": 0, "optimalScore": 0}]}, {"timestamp": 1687813200, "probability": 100, "utcOffset": -4, "surf": {"min": 1, "max": 2, "optimalScore": 0, "plus": false, "humanRelation": "Knee to thigh", "raw": {"min": 0.23802999999999996, "max": 1.259426}}, "power": 1.32108, "swells": [{"height": 1.60761, "period": 8, "impact": 0.4177, "power": 0.88935, "direction": 125.58, "directionMin": 119.4, "optimalScore": 0}, {"height": 0.88583, "period": 10, "impact": 0.2952, "power": 0.35443, "direction": 122.71, "directionMin": 117.80999999999999, "optimalScore": 0}, {"height": 0, "period": 0, "impact": 0, "power": 0, "direction": 0, "directionMin": 0, "optimalScore": 0}, {"height": 0.49213, "period": 3, "impact": 0.1202, "power": 0.03168, "direction": 52.7, "directionMin": 43.935, "optimalScore": 0}, {"height": 0.26247, "period": 15, "impact": 0.167, "power": 0.04562, "direction": 112.98, "directionMin": 108.42500000000001, "optimalScore": 0}, {"height": 0, "period": 0, "impact": 0, "power": 0, "direction": 0, "directionMin": 0, "optimalScore": 0}]}, {"timestamp": 1687816800, "probability": 100, "utcOffset": -4, "surf": {"min": 0, "max": 1, "optimalScore": 0, "plus": false, "humanRelation": "Shin to knee", "raw": {"min": 0, "max": 1}}, "power": 1.34625, "swells": [{"height": 1.54199, "period": 7, "impact": 0.3855, "power": 0.79547, "direction": 124.95, "directionMin": 118.765, "optimalScore": 0}, {"height": 1.01706, "period": 10, "impact": 0.3183, "power": 0.46393, "direction": 125.14, "directionMin": 120.1, "optimalScore": 0}, {"height": 0, "period": 0, "impact": 0, "power": 0, "direction": 0, "directionMin": 0, "optimalScore": 0}, {"height": 0.55774, "period": 3, "impact": 0.1291, "power": 0.04098, "direction": 51.96, "directionMin": 42.885000000000005, "optimalScore": 0}, {"height": 0.26247, "period": 15, "impact": 0.167, "power": 0.04587, "direction": 111.93, "directionMin": 107.42500000000001, "optimalScore": 0}, {"height": 0, "period": 0, "impact": 0, "power": 0, "direction": 0, "directionMin": 0, "optimalScore": 0}]}, {"timestamp": 1687820400, "probability": 100, "utcOffset": -4, "surf": {"min": 1, "max": 2, "optimalScore": 0, "plus": false, "humanRelation": "Knee to thigh", "raw": {"min": 0.1449716666666666, "max": 1.1796366666666667}}, "power": 1.39399, "swells": [{"height": 1.60761, "period": 8, "impact": 0.3897, "power": 0.89288, "direction": 125.49, "directionMin": 119.425, "optimalScore": 0}, {"height": 0.91864, "period": 10, "impact": 0.2812, "power": 0.37656, "direction": 123.59, "directionMin": 118.44500000000001, "optimalScore": 0}, {"height": 0, "period": 0, "impact": 0, "power": 0, "direction": 0, "directionMin": 0, "optimalScore": 0}, {"height": 0.72178, "period": 3, "impact": 0.156, "power": 0.06649, "direction": 52.67, "directionMin": 43.235, "optimalScore": 0}, {"height": 0.29528, "period": 15, "impact": 0.1731, "power": 0.05806, "direction": 112.02, "directionMin": 107.505, "optimalScore": 0}, {"height": 0, "period": 0, "impact": 0, "power": 0, "direction": 0, "directionMin": 0, "optimalScore": 0}]}, {"timestamp": 1687824000, "probability": 100, "utcOffset": -4, "surf": {"min": 1, "max": 2, "optimalScore": 0, "plus": false, "humanRelation": "Knee to thigh", "raw": {"min": 0.1951033333333334, "max": 1.2111033333333334}}, "power": 1.37873, "swells": [{"height": 1.54199, "period": 7, "impact": 0.3574, "power": 0.80197, "direction": 126.37, "directionMin": 120.31, "optimalScore": 0}, {"height": 0.98425, "period": 10, "impact": 0.3, "power": 0.42521, "direction": 122.32, "directionMin": 117.27499999999999, "optimalScore": 0}, {"height": 0, "period": 0, "impact": 0, "power": 0, "direction": 0, "directionMin": 0, "optimalScore": 0}, {"height": 0.85302, "period": 3, "impact": 0.1764, "power": 0.09353, "direction": 58.26, "directionMin": 47.23, "optimalScore": 0}, {"height": 0.29528, "period": 15, "impact": 0.1662, "power": 0.05802, "direction": 112.03, "directionMin": 107.505, "optimalScore": 0}, {"height": 0, "period": 0, "impact": 0, "power": 0, "direction": 0, "directionMin": 0, "optimalScore": 0}]}, {"timestamp": 1687827600, "probability": 100, "utcOffset": -4, "surf": {"min": 1, "max": 2, "optimalScore": 0, "plus": false, "humanRelation": "Knee to thigh", "raw": {"min": 0.34062499999999996, "max": 1.3916000000000002}}, "power": 1.4847, "swells": [{"height": 1.64042, "period": 7, "impact": 0.3706, "power": 0.90762, "direction": 124.25, "directionMin": 116.945, "optimalScore": 0}, {"height": 0.98425, "period": 10, "impact": 0.2946, "power": 0.42168, "direction": 122.41, "directionMin": 117.33, "optimalScore": 0}, {"height": 0, "period": 0, "impact": 0, "power": 0, "direction": 0, "directionMin": 0, "optimalScore": 0}, {"height": 0.7874, "period": 3, "impact": 0.1653, "power": 0.08421, "direction": 53.4, "directionMin": 44.075, "optimalScore": 0}, {"height": 0.32808, "period": 15, "impact": 0.1696, "power": 0.07119, "direction": 112.84, "directionMin": 108.37, "optimalScore": 0}, {"height": 0, "period": 0, "impact": 0, "power": 0, "direction": 0, "directionMin": 0, "optimalScore": 0}]}, {"timestamp": 1687831200, "probability": null, "utcOffset": -4, "surf": {"min": 1, "max": 2, "optimalScore": 0, "plus": false, "humanRelation": "Knee to thigh", "raw": {"min": 0.45340666666666674, "max": 1.5209466666666667}}, "power": 1.49806, "swells": [{"height": 1.67323, "period": 7, "impact": 0.3864, "power": 0.94556, "direction": 123.72, "directionMin": 116.17999999999999, "optimalScore": 0}, {"height": 0.98425, "period": 9, "impact": 0.2837, "power": 0.4177, "direction": 122.56, "directionMin": 117.47500000000001, "optimalScore": 0}, {"height": 0, "period": 0, "impact": 0, "power": 0, "direction": 0, "directionMin": 0, "optimalScore": 0}, {"height": 0.72178, "period": 3, "impact": 0.1618, "power": 0.0767, "direction": 50.99, "directionMin": 42.465, "optimalScore": 0}, {"height": 0.29528, "period": 15, "impact": 0.1681, "power": 0.0581, "direction": 111.19, "directionMin": 107.015, "optimalScore": 0}, {"height": 0, "period": 0, "impact": 0, "power": 0, "direction": 0, "directionMin": 0, "optimalScore": 0}]}, {"timestamp": 1687834800, "probability": null, "utcOffset": -4, "surf": {"min": 1, "max": 2, "optimalScore": 0, "plus": false, "humanRelation": "Knee to thigh", "raw": {"min": 0.5441083333333333, "max": 1.6157833333333333}}, "power": 1.53996, "swells": [{"height": 1.67323, "period": 7, "impact": 0.3806, "power": 0.93663, "direction": 122.81, "directionMin": 115.21000000000001, "optimalScore": 0}, {"height": 1.04987, "period": 9, "impact": 0.2938, "power": 0.46922, "direction": 124.98, "directionMin": 119.635, "optimalScore": 0}, {"height": 0, "period": 0, "impact": 0, "power": 0, "direction": 0, "directionMin": 0, "optimalScore": 0}, {"height": 0.75459, "period": 3, "impact": 0.1713, "power": 0.08824, "direction": 49.88, "directionMin": 41.46, "optimalScore": 0}, {"height": 0.26247, "period": 15, "impact": 0.1543, "power": 0.04587, "direction": 111.32, "directionMin": 107.05, "optimalScore": 0}, {"height": 0, "period": 0, "impact": 0, "power": 0, "direction": 0, "directionMin": 0, "optimalScore": 0}]}]}, "permissions": {"data": [], "violations": [{"code": 4001, "message": "User does not have optional permission:sl_premium-forecasts", "permission": {"name": "sl_premium-forecasts", "required": false}}, {"code": 4001, "message": "User does not have optional permission:sl_premium-cams", "permission": {"name": "sl_premium-cams", "required": false}}]}}