{"associated": {"units": {"temperature": "F", "tideHeight": "FT", "swellHeight": "FT", "waveHeight": "FT", "windSpeed": "KTS", "pressure": "MB"}, "utcOffset": -4, "location": {"lon": -70.79141, "lat": 42.9376373334092}, "forecastLocation": {"lon": -70.78551292419434, "lat": 42.93694613058707}, "offshoreLocation": {"lon": -70.75, "lat": 42.9}, "runInitializationTimestamp": 1682035200}, "data": {"wave": [{"timestamp": 1682049600, "probability": 100, "utcOffset": -4, "surf": {"min": 1, "max": 2, "optimalScore": 0, "plus": false, "humanRelation": "Knee to thigh", "raw": {"min": 0.004807272727272771, "max": 1.0075090909090907}}, "swells": [{"height": 0.59055, "period": 3, "impact": 0.1195, "direction": 134.58, "directionMin": 125.055, "optimalScore": 0}, {"height": 0.82021, "period": 8, "impact": 0.4257, "direction": 88.65, "directionMin": 84.88000000000001, "optimalScore": 0}, {"height": 0.32808, "period": 6, "impact": 0.1276, "direction": 135.04, "directionMin": 130.35999999999999, "optimalScore": 0}, {"height": 0.3937, "period": 11, "impact": 0.2554, "direction": 114.89, "directionMin": 109.37, "optimalScore": 0}, {"height": 0.19685, "period": 3, "impact": 0.0719, "direction": 33.39, "directionMin": 24.605, "optimalScore": 0}, {"height": 0, "period": 0, "impact": 0, "direction": 0, "directionMin": 0, "optimalScore": 0}]}, {"timestamp": 1682053200, "probability": 100, "utcOffset": -4, "surf": {"min": 1, "max": 2, "optimalScore": 0, "plus": false, "humanRelation": "Knee to thigh", "raw": {"min": 0.005651818181818258, "max": 1.0088372727272725}}, "swells": [{"height": 0.55774, "period": 3, "impact": 0.1277, "direction": 135.89, "directionMin": 127.07999999999998, "optimalScore": 0}, {"height": 0.82021, "period": 8, "impact": 0.468, "direction": 88.81, "directionMin": 84.965, "optimalScore": 0}, {"height": 0.32808, "period": 7, "impact": 0.1416, "direction": 134.26, "directionMin": 129.295, "optimalScore": 0}, {"height": 0.36089, "period": 11, "impact": 0.2627, "direction": 115.36, "directionMin": 109.76, "optimalScore": 0}, {"height": 0, "period": 0, "impact": 0, "direction": 0, "directionMin": 0, "optimalScore": 0}, {"height": 0, "period": 0, "impact": 0, "direction": 0, "directionMin": 0, "optimalScore": 0}]}, {"timestamp": 1682056800, "probability": 100, "utcOffset": -4, "surf": {"min": 1, "max": 2, "optimalScore": 0, "plus": false, "humanRelation": "Knee to thigh", "raw": {"min": 0.03062636363636373, "max": 1.0478654545454544}}, "swells": [{"height": 0.55774, "period": 3, "impact": 0.1289, "direction": 136.28, "directionMin": 127.265, "optimalScore": 0}, {"height": 0.85302, "period": 8, "impact": 0.4763, "direction": 87.82, "directionMin": 82.17999999999999, "optimalScore": 0}, {"height": 0.32808, "period": 6, "impact": 0.137, "direction": 134.8, "directionMin": 130.13000000000002, "optimalScore": 0}, {"height": 0.36089, "period": 11, "impact": 0.2577, "direction": 115.59, "directionMin": 110.02000000000001, "optimalScore": 0}, {"height": 0, "period": 0, "impact": 0, "direction": 0, "directionMin": 0, "optimalScore": 0}, {"height": 0, "period": 0, "impact": 0, "direction": 0, "directionMin": 0, "optimalScore": 0}]}, {"timestamp": 1682060400, "probability": 93.33333333333331, "utcOffset": -4, "surf": {"min": 1, "max": 2, "optimalScore": 0, "plus": false, "humanRelation": "Knee to thigh", "raw": {"min": 0.028450909090909082, "max": 1.0444536363636363}}, "swells": [{"height": 0.52493, "period": 3, "impact": 0.1286, "direction": 137.15, "directionMin": 128.69, "optimalScore": 0}, {"height": 0.85302, "period": 8, "impact": 0.4809, "direction": 88.08, "directionMin": 82.945, "optimalScore": 0}, {"height": 0.29528, "period": 6, "impact": 0.1305, "direction": 134.55, "directionMin": 129.565, "optimalScore": 0}, {"height": 0.36089, "period": 11, "impact": 0.26, "direction": 116.19, "directionMin": 110.995, "optimalScore": 0}, {"height": 0, "period": 0, "impact": 0, "direction": 0, "directionMin": 0, "optimalScore": 0}, {"height": 0, "period": 0, "impact": 0, "direction": 0, "directionMin": 0, "optimalScore": 0}]}, {"timestamp": 1682064000, "probability": 93.33333333333331, "utcOffset": -4, "surf": {"min": 1, "max": 2, "optimalScore": 0, "plus": false, "humanRelation": "Knee to thigh", "raw": {"min": 0.028845454545454507, "max": 1.0450718181818182}}, "swells": [{"height": 0.52493, "period": 3, "impact": 0.1301, "direction": 137.04, "directionMin": 127.86999999999999, "optimalScore": 0}, {"height": 0.85302, "period": 8, "impact": 0.481, "direction": 87.86, "directionMin": 83.325, "optimalScore": 0}, {"height": 0.29528, "period": 6, "impact": 0.1299, "direction": 134.2, "directionMin": 129.225, "optimalScore": 0}, {"height": 0.36089, "period": 11, "impact": 0.2589, "direction": 116.37, "directionMin": 111.205, "optimalScore": 0}, {"height": 0, "period": 0, "impact": 0, "direction": 0, "directionMin": 0, "optimalScore": 0}, {"height": 0, "period": 0, "impact": 0, "direction": 0, "directionMin": 0, "optimalScore": 0}]}, {"timestamp": 1682067600, "probability": 93.33333333333331, "utcOffset": -4, "surf": {"min": 0, "max": 1, "optimalScore": 0, "plus": false, "humanRelation": "Shin to knee", "raw": {"min": 0, "max": 1}}, "swells": [{"height": 0.49213, "period": 3, "impact": 0.1082, "direction": 138.64, "directionMin": 132.17, "optimalScore": 0}, {"height": 0.82021, "period": 8, "impact": 0.4499, "direction": 88.52, "directionMin": 84.91, "optimalScore": 0}, {"height": 0.29528, "period": 6, "impact": 0.1256, "direction": 134.83, "directionMin": 129.98000000000002, "optimalScore": 0}, {"height": 0.36089, "period": 11, "impact": 0.2502, "direction": 116.44, "directionMin": 111.33, "optimalScore": 0}, {"height": 0, "period": 0, "impact": 0, "direction": 0, "directionMin": 0, "optimalScore": 0}, {"height": 0.26247, "period": 2, "impact": 0.0662, "direction": 48.37, "directionMin": 41.254999999999995, "optimalScore": 0}]}, {"timestamp": 1682071200, "probability": 63.33333333333333, "utcOffset": -4, "surf": {"min": 0, "max": 1, "optimalScore": 0, "plus": false, "humanRelation": "Shin to knee", "raw": {"min": 0, "max": 1}}, "swells": [{"height": 0.42651, "period": 3, "impact": 0.0811, "direction": 139.93, "directionMin": 134.335, "optimalScore": 0}, {"height": 0.82021, "period": 8, "impact": 0.3845, "direction": 88.23, "directionMin": 84.805, "optimalScore": 0}, {"height": 0.26247, "period": 6, "impact": 0.0994, "direction": 134.95, "directionMin": 129.95499999999998, "optimalScore": 0}, {"height": 0.3937, "period": 11, "impact": 0.2267, "direction": 115.5, "directionMin": 110.005, "optimalScore": 0}, {"height": 0, "period": 0, "impact": 0, "direction": 0, "directionMin": 0, "optimalScore": 0}, {"height": 0.85302, "period": 2, "impact": 0.2083, "direction": 54.29, "directionMin": 43.175, "optimalScore": 0}]}, {"timestamp": 1682074800, "probability": 63.33333333333333, "utcOffset": -4, "surf": {"min": 0, "max": 1, "optimalScore": 0, "plus": false, "humanRelation": "Shin to knee", "raw": {"min": -0.005896666666666661, "max": 0.990785}}, "swells": [{"height": 0, "period": 0, "impact": 0, "direction": 0, "directionMin": 0, "optimalScore": 0}, {"height": 0.82021, "period": 8, "impact": 0.3786, "direction": 88.26, "directionMin": 84.94500000000001, "optimalScore": 0}, {"height": 0.26247, "period": 6, "impact": 0.0981, "direction": 134.98, "directionMin": 129.98499999999999, "optimalScore": 0}, {"height": 0.3937, "period": 11, "impact": 0.2233, "direction": 116.32, "directionMin": 111.125, "optimalScore": 0}, {"height": 1.11549, "period": 3, "impact": 0.3, "direction": 69.62, "directionMin": 52.95, "optimalScore": 0}, {"height": 0, "period": 0, "impact": 0, "direction": 0, "directionMin": 0, "optimalScore": 0}]}, {"timestamp": 1682078400, "probability": 63.33333333333333, "utcOffset": -4, "surf": {"min": 0, "max": 1, "optimalScore": 0, "plus": false, "humanRelation": "Shin to knee", "raw": {"min": -0.03737333333333326, "max": 0.9416000000000001}}, "swells": [{"height": 0, "period": 0, "impact": 0, "direction": 0, "directionMin": 0, "optimalScore": 0}, {"height": 0.7874, "period": 8, "impact": 0.3522, "direction": 88.2, "directionMin": 84.93, "optimalScore": 0}, {"height": 0.26247, "period": 6, "impact": 0.0944, "direction": 134.55, "directionMin": 129.42000000000002, "optimalScore": 0}, {"height": 0.3937, "period": 11, "impact": 0.215, "direction": 116.49, "directionMin": 111.32499999999999, "optimalScore": 0}, {"height": 1.27953, "period": 3, "impact": 0.3384, "direction": 73.05, "directionMin": 57.655, "optimalScore": 0}, {"height": 0, "period": 0, "impact": 0, "direction": 0, "directionMin": 0, "optimalScore": 0}]}, {"timestamp": 1682082000, "probability": 60, "utcOffset": -4, "surf": {"min": 0, "max": 1, "optimalScore": 0, "plus": false, "humanRelation": "Shin to knee", "raw": {"min": -0.023930000000000007, "max": 0.962605}}, "swells": [{"height": 0.16404, "period": 8, "impact": 0.0847, "direction": 125.94, "directionMin": 122.74, "optimalScore": 0}, {"height": 0.7874, "period": 8, "impact": 0.312, "direction": 88.17, "directionMin": 84.93, "optimalScore": 0}, {"height": 0.26247, "period": 6, "impact": 0.081, "direction": 135.84, "directionMin": 131.03, "optimalScore": 0}, {"height": 0.42651, "period": 11, "impact": 0.2018, "direction": 116.55, "directionMin": 111.445, "optimalScore": 0}, {"height": 1.34514, "period": 3, "impact": 0.3205, "direction": 75.95, "directionMin": 60.52, "optimalScore": 0}, {"height": 0, "period": 0, "impact": 0, "direction": 0, "directionMin": 0, "optimalScore": 0}]}, {"timestamp": 1682085600, "probability": 60, "utcOffset": -4, "surf": {"min": 0, "max": 1, "optimalScore": 0, "plus": false, "humanRelation": "Shin to knee", "raw": {"min": -0.0015366666666666307, "max": 0.9975900000000001}}, "swells": [{"height": 0.16404, "period": 8, "impact": 0.0842, "direction": 127.06, "directionMin": 123.49000000000001, "optimalScore": 0}, {"height": 0.7874, "period": 8, "impact": 0.3103, "direction": 88.2, "directionMin": 84.905, "optimalScore": 0}, {"height": 0.22966, "period": 6, "impact": 0.0737, "direction": 136.81, "directionMin": 132.505, "optimalScore": 0}, {"height": 0.42651, "period": 11, "impact": 0.2009, "direction": 116.31, "directionMin": 111.025, "optimalScore": 0}, {"height": 1.37795, "period": 3, "impact": 0.3309, "direction": 77.94, "directionMin": 62.019999999999996, "optimalScore": 0}, {"height": 0, "period": 0, "impact": 0, "direction": 0, "directionMin": 0, "optimalScore": 0}]}, {"timestamp": 1682089200, "probability": 60, "utcOffset": -4, "surf": {"min": 1, "max": 2, "optimalScore": 0, "plus": false, "humanRelation": "Knee to thigh", "raw": {"min": 0.0015066666666667672, "max": 1.002355}}, "swells": [{"height": 0.16404, "period": 8, "impact": 0.0849, "direction": 127.11, "directionMin": 123.55499999999999, "optimalScore": 0}, {"height": 0.75459, "period": 8, "impact": 0.3018, "direction": 88.18, "directionMin": 84.89500000000001, "optimalScore": 0}, {"height": 0.22966, "period": 6, "impact": 0.0743, "direction": 136.83, "directionMin": 132.29500000000002, "optimalScore": 0}, {"height": 0.42651, "period": 11, "impact": 0.2021, "direction": 116.41, "directionMin": 111.19, "optimalScore": 0}, {"height": 1.37795, "period": 3, "impact": 0.3369, "direction": 79.1, "directionMin": 62.80499999999999, "optimalScore": 0}, {"height": 0, "period": 0, "impact": 0, "direction": 0, "directionMin": 0, "optimalScore": 0}]}, {"timestamp": 1682092800, "probability": 66.66666666666666, "utcOffset": -4, "surf": {"min": 0, "max": 1, "optimalScore": 0, "plus": false, "humanRelation": "Shin to knee", "raw": {"min": 0, "max": 1}}, "swells": [{"height": 0.16404, "period": 8, "impact": 0.0848, "direction": 127.19, "directionMin": 123.645, "optimalScore": 0}, {"height": 0.75459, "period": 8, "impact": 0.3013, "direction": 88.15, "directionMin": 84.855, "optimalScore": 0}, {"height": 0.22966, "period": 6, "impact": 0.0743, "direction": 136.98, "directionMin": 132.45, "optimalScore": 0}, {"height": 0.42651, "period": 11, "impact": 0.2014, "direction": 116.58, "directionMin": 111.4, "optimalScore": 0}, {"height": 1.37795, "period": 3, "impact": 0.3382, "direction": 79.9, "directionMin": 63.425000000000004, "optimalScore": 0}, {"height": 0, "period": 0, "impact": 0, "direction": 0, "directionMin": 0, "optimalScore": 0}]}, {"timestamp": 1682096400, "probability": 66.66666666666666, "utcOffset": -4, "surf": {"min": 1, "max": 2, "optimalScore": 0, "plus": false, "humanRelation": "Knee to thigh", "raw": {"min": 0.021308333333333374, "max": 1.0332883333333334}}, "swells": [{"height": 0.16404, "period": 8, "impact": 0.0787, "direction": 128.43, "directionMin": 125.17, "optimalScore": 0}, {"height": 0.75459, "period": 8, "impact": 0.2997, "direction": 87.96, "directionMin": 84.79499999999999, "optimalScore": 0}, {"height": 0.22966, "period": 6, "impact": 0.0739, "direction": 136.57, "directionMin": 131.62, "optimalScore": 0}, {"height": 0.45932, "period": 11, "impact": 0.2104, "direction": 116.53, "directionMin": 111.455, "optimalScore": 0}, {"height": 1.37795, "period": 3, "impact": 0.3373, "direction": 80.4, "directionMin": 63.845000000000006, "optimalScore": 0}, {"height": 0, "period": 0, "impact": 0, "direction": 0, "directionMin": 0, "optimalScore": 0}]}, {"timestamp": 1682100000, "probability": 66.66666666666666, "utcOffset": -4, "surf": {"min": 1, "max": 2, "optimalScore": 0, "plus": false, "humanRelation": "Knee to thigh", "raw": {"min": 0.025296666666666745, "max": 1.0395266666666667}}, "swells": [{"height": 0.16404, "period": 8, "impact": 0.0801, "direction": 128.46, "directionMin": 125.19500000000001, "optimalScore": 0}, {"height": 0.72178, "period": 8, "impact": 0.2947, "direction": 87.91, "directionMin": 84.725, "optimalScore": 0}, {"height": 0.22966, "period": 6, "impact": 0.0754, "direction": 136.77, "directionMin": 131.83, "optimalScore": 0}, {"height": 0.45932, "period": 11, "impact": 0.2128, "direction": 116.69, "directionMin": 111.66499999999999, "optimalScore": 0}, {"height": 1.34514, "period": 3, "impact": 0.3371, "direction": 81.6, "directionMin": 64.74, "optimalScore": 0}, {"height": 0, "period": 0, "impact": 0, "direction": 0, "directionMin": 0, "optimalScore": 0}]}, {"timestamp": 1682103600, "probability": 65.33333333333333, "utcOffset": -4, "surf": {"min": 1, "max": 2, "optimalScore": 0, "plus": false, "humanRelation": "Knee to thigh", "raw": {"min": 0.04057500000000003, "max": 1.0633949999999999}}, "swells": [{"height": 0, "period": 0, "impact": 0, "direction": 0, "directionMin": 0, "optimalScore": 0}, {"height": 0.72178, "period": 8, "impact": 0.3181, "direction": 87.63, "directionMin": 84.52, "optimalScore": 0}, {"height": 0.22966, "period": 6, "impact": 0.0814, "direction": 136.83, "directionMin": 131.92000000000002, "optimalScore": 0}, {"height": 0.49213, "period": 10, "impact": 0.2387, "direction": 116.07, "directionMin": 110.96, "optimalScore": 0}, {"height": 1.34514, "period": 3, "impact": 0.3619, "direction": 83.17, "directionMin": 65.92, "optimalScore": 0}, {"height": 0, "period": 0, "impact": 0, "direction": 0, "directionMin": 0, "optimalScore": 0}]}, {"timestamp": 1682107200, "probability": 65.33333333333333, "utcOffset": -4, "surf": {"min": 1, "max": 2, "optimalScore": 0, "plus": false, "humanRelation": "Knee to thigh", "raw": {"min": 0.02727333333333337, "max": 1.0426033333333333}}, "swells": [{"height": 0, "period": 0, "impact": 0, "direction": 0, "directionMin": 0, "optimalScore": 0}, {"height": 0.68898, "period": 8, "impact": 0.3153, "direction": 87.56, "directionMin": 84.44, "optimalScore": 0}, {"height": 0.22966, "period": 6, "impact": 0.0836, "direction": 137.01, "directionMin": 132.26999999999998, "optimalScore": 0}, {"height": 0.49213, "period": 10, "impact": 0.2447, "direction": 116.11, "directionMin": 111.03, "optimalScore": 0}, {"height": 1.27953, "period": 3, "impact": 0.3564, "direction": 85.48, "directionMin": 67.845, "optimalScore": 0}, {"height": 0, "period": 0, "impact": 0, "direction": 0, "directionMin": 0, "optimalScore": 0}]}, {"timestamp": 1682110800, "probability": 65.33333333333333, "utcOffset": -4, "surf": {"min": 1, "max": 2, "optimalScore": 0, "plus": false, "humanRelation": "Knee to thigh", "raw": {"min": 0.016971666666666718, "max": 1.0265216666666666}}, "swells": [{"height": 0, "period": 0, "impact": 0, "direction": 0, "directionMin": 0, "optimalScore": 0}, {"height": 0.68898, "period": 8, "impact": 0.3209, "direction": 87.77, "directionMin": 84.445, "optimalScore": 0}, {"height": 0.19685, "period": 6, "impact": 0.0701, "direction": 138.78, "directionMin": 134.48, "optimalScore": 0}, {"height": 0.52493, "period": 10, "impact": 0.2609, "direction": 117.41, "directionMin": 112.1, "optimalScore": 0}, {"height": 1.24672, "period": 3, "impact": 0.3481, "direction": 88.42, "directionMin": 70.505, "optimalScore": 0}, {"height": 0, "period": 0, "impact": 0, "direction": 0, "directionMin": 0, "optimalScore": 0}]}, {"timestamp": 1682114400, "probability": 63.33333333333333, "utcOffset": -4, "surf": {"min": 0, "max": 1, "optimalScore": 0, "plus": false, "humanRelation": "Shin to knee", "raw": {"min": 0, "max": 1}}, "swells": [{"height": 0, "period": 0, "impact": 0, "direction": 0, "directionMin": 0, "optimalScore": 0}, {"height": 0.68898, "period": 8, "impact": 0.3313, "direction": 88.17, "directionMin": 84.69, "optimalScore": 0}, {"height": 0.19685, "period": 6, "impact": 0.0722, "direction": 138.58, "directionMin": 134.38000000000002, "optimalScore": 0}, {"height": 0.52493, "period": 10, "impact": 0.2557, "direction": 118.29, "directionMin": 113.27000000000001, "optimalScore": 0}, {"height": 1.21391, "period": 3, "impact": 0.3407, "direction": 92.6, "directionMin": 74.405, "optimalScore": 0}, {"height": 0, "period": 0, "impact": 0, "direction": 0, "directionMin": 0, "optimalScore": 0}]}, {"timestamp": 1682118000, "probability": 63.33333333333333, "utcOffset": -4, "surf": {"min": 0, "max": 1, "optimalScore": 0, "plus": false, "humanRelation": "Shin to knee", "raw": {"min": 0.037304166666666694, "max": 0.9749516666666668}}, "swells": [{"height": 0.95144, "period": 3, "impact": 0.1972, "direction": 122.23, "directionMin": 111.47, "optimalScore": 0}, {"height": 0.68898, "period": 8, "impact": 0.2995, "direction": 88.1, "directionMin": 84.595, "optimalScore": 0}, {"height": 0.19685, "period": 6, "impact": 0.0652, "direction": 138.63, "directionMin": 134.285, "optimalScore": 0}, {"height": 0.52493, "period": 10, "impact": 0.231, "direction": 118.7, "directionMin": 113.61, "optimalScore": 0}, {"height": 0, "period": 0, "impact": 0, "direction": 0, "directionMin": 0, "optimalScore": 0}, {"height": 0.72178, "period": 3, "impact": 0.2071, "direction": 56.72, "directionMin": 48.285, "optimalScore": 0}]}, {"timestamp": 1682121600, "probability": 63.33333333333333, "utcOffset": -4, "surf": {"min": 0, "max": 1, "optimalScore": 0, "plus": false, "humanRelation": "Shin to knee", "raw": {"min": 0.07785833333333336, "max": 0.9549833333333333}}, "swells": [{"height": 1.14829, "period": 3, "impact": 0.246, "direction": 121.39, "directionMin": 109.885, "optimalScore": 0}, {"height": 0.65617, "period": 8, "impact": 0.3027, "direction": 87.15, "directionMin": 83.985, "optimalScore": 0}, {"height": 0, "period": 0, "impact": 0, "direction": 0, "directionMin": 0, "optimalScore": 0}, {"height": 0.55774, "period": 10, "impact": 0.2629, "direction": 116.89, "directionMin": 111.07, "optimalScore": 0}, {"height": 0, "period": 0, "impact": 0, "direction": 0, "directionMin": 0, "optimalScore": 0}, {"height": 0.62336, "period": 3, "impact": 0.1883, "direction": 53.02, "directionMin": 46.005, "optimalScore": 0}]}, {"timestamp": 1682125200, "probability": 70, "utcOffset": -4, "surf": {"min": 1, "max": 2, "optimalScore": 0, "plus": false, "humanRelation": "Knee to thigh", "raw": {"min": 0.1782125, "max": 1.028465}}, "swells": [{"height": 1.44357, "period": 3, "impact": 0.3424, "direction": 114.35, "directionMin": 98.175, "optimalScore": 0}, {"height": 0.62336, "period": 8, "impact": 0.308, "direction": 86.91, "directionMin": 83.905, "optimalScore": 0}, {"height": 0.19685, "period": 6, "impact": 0.0715, "direction": 138.37, "directionMin": 133.84, "optimalScore": 0}, {"height": 0.55774, "period": 10, "impact": 0.2781, "direction": 116.72, "directionMin": 111.01, "optimalScore": 0}, {"height": 0, "period": 0, "impact": 0, "direction": 0, "directionMin": 0, "optimalScore": 0}, {"height": 0, "period": 0, "impact": 0, "direction": 0, "directionMin": 0, "optimalScore": 0}]}, {"timestamp": 1682128800, "probability": null, "utcOffset": -4, "surf": {"min": 1, "max": 2, "optimalScore": 0, "plus": false, "humanRelation": "Knee to thigh", "raw": {"min": 0.2706266666666667, "max": 1.0895166666666667}}, "swells": [{"height": 1.5748, "period": 4, "impact": 0.3816, "direction": 120.53, "directionMin": 105.04, "optimalScore": 0}, {"height": 0.62336, "period": 8, "impact": 0.3263, "direction": 86.79, "directionMin": 83.59500000000001, "optimalScore": 0}, {"height": 0, "period": 0, "impact": 0, "direction": 0, "directionMin": 0, "optimalScore": 0}, {"height": 0.59055, "period": 10, "impact": 0.2921, "direction": 118.96, "directionMin": 112.49, "optimalScore": 0}, {"height": 0, "period": 0, "impact": 0, "direction": 0, "directionMin": 0, "optimalScore": 0}, {"height": 0, "period": 0, "impact": 0, "direction": 0, "directionMin": 0, "optimalScore": 0}]}, {"timestamp": 1682132400, "probability": null, "utcOffset": -4, "surf": {"min": 1, "max": 2, "optimalScore": 0, "plus": false, "humanRelation": "Knee to thigh", "raw": {"min": 0.3170908333333333, "max": 1.0787783333333334}}, "swells": [{"height": 1.60761, "period": 4, "impact": 0.3534, "direction": 123.79, "directionMin": 108.685, "optimalScore": 0}, {"height": 0.62336, "period": 8, "impact": 0.3066, "direction": 86.26, "directionMin": 82.81, "optimalScore": 0}, {"height": 0.19685, "period": 7, "impact": 0.076, "direction": 138.66, "directionMin": 134.53, "optimalScore": 0}, {"height": 0.52493, "period": 10, "impact": 0.264, "direction": 116.35, "directionMin": 110.80999999999999, "optimalScore": 0}, {"height": 0, "period": 0, "impact": 0, "direction": 0, "directionMin": 0, "optimalScore": 0}, {"height": 0, "period": 0, "impact": 0, "direction": 0, "directionMin": 0, "optimalScore": 0}]}]}, "permissions": {"data": [], "violations": [{"code": 4001, "message": "User does not have optional permission:sl_premium-forecasts", "permission": {"name": "sl_premium-forecasts", "required": false}}, {"code": 4001, "message": "User does not have optional permission:sl_premium-cams", "permission": {"name": "sl_premium-cams", "required": false}}]}}